evileg_core/__init__.py
evileg_core/admin.py
evileg_core/apps.py
evileg_core/backends.py
evileg_core/decorators.py
evileg_core/fields.py
evileg_core/filters.py
evileg_core/forms.py
evileg_core/managers.py
evileg_core/mixins.py
evileg_core/models.py
evileg_core/settings.py
evileg_core/shortcuts.py
evileg_core/tests.py
evileg_core/urls.py
evileg_core/utils.py
evileg_core/views.py
evileg_core/widgets.py
evileg_core/cache/decorators.py
evileg_core/cache/receivers.py
evileg_core/cache/utils.py
evileg_core/extensions/__init__.py
evileg_core/extensions/video.py
evileg_core/locale/en/LC_MESSAGES/django.mo
evileg_core/locale/en/LC_MESSAGES/django.po
evileg_core/locale/ru/LC_MESSAGES/django.mo
evileg_core/locale/ru/LC_MESSAGES/django.po
evileg_core/locale/uk/LC_MESSAGES/django.mo
evileg_core/locale/uk/LC_MESSAGES/django.po
evileg_core/migrations/__init__.py
evileg_core/static/css/cropper.css
evileg_core/static/css/cropper.min.css
evileg_core/static/css/evileg_core.css
evileg_core/static/css/evileg_core.min.css
evileg_core/static/css/evileg_core_admin.css
evileg_core/static/css/evileg_core_darcula.css
evileg_core/static/css/evileg_core_darcula.min.css
evileg_core/static/css/materialdesignicons.css
evileg_core/static/css/materialdesignicons.css.map
evileg_core/static/css/materialdesignicons.min.css
evileg_core/static/css/materialdesignicons.min.css.map
evileg_core/static/images/file.svg
evileg_core/static/js/cropper.common.js
evileg_core/static/js/cropper.esm.js
evileg_core/static/js/cropper.js
evileg_core/static/js/cropper.min.js
evileg_core/static/js/evileg_core.js
evileg_core/static/js/evileg_core.js.map
evileg_core/static/js/evileg_core.min.js
evileg_core/static/js/jquery-3.3.1.min.js
evileg_core/static/js/markdown.js
evileg_core/static/js/markdown.min.js
evileg_core/static/js/popper.min.js
evileg_core/templates/evileg_core/breadcrumb_active.html
evileg_core/templates/evileg_core/breadcrumb_home.html
evileg_core-0.0.5.dist-info/DESCRIPTION.rst
evileg_core-0.0.5.dist-info/METADATA
evileg_core-0.0.5.dist-info/RECORD
evileg_core-0.0.5.dist-info/WHEEL
evileg_core-0.0.5.dist-info/metadata.json
evileg_core-0.0.5.dist-info/top_level.txt
