Metadata-Version: 2.0
Name: evileg-core
Version: 0.0.5
Summary: (ESNF-C) EVILEG Social Network Framework - Core Module.
Home-page: https://github.com/EVILEG/evileg-core/
Author: Evgenii Legotckoi
Author-email: evileg@evileg.com
License: LGPLv3 License
Keywords: django evileg core
Platform: UNKNOWN
Classifier: Development Status :: 1 - Planning
Classifier: Environment :: Web Environment
Classifier: Framework :: Django
Classifier: Framework :: Django :: 2.0
Classifier: Intended Audience :: Developers
Classifier: License :: OSI Approved :: GNU Lesser General Public License v3 (LGPLv3)
Classifier: Operating System :: OS Independent
Classifier: Programming Language :: Python
Classifier: Programming Language :: Python :: 3.5
Classifier: Programming Language :: Python :: 3.6
Classifier: Programming Language :: Python :: 3.7
Classifier: Topic :: Internet :: WWW/HTTP
Classifier: Topic :: Internet :: WWW/HTTP :: Dynamic Content
Requires-Dist: Django
Requires-Dist: Markdown
Requires-Dist: beautifulsoup4
Requires-Dist: django-bootstrap4
Requires-Dist: django-redis
Requires-Dist: djangocodemirror
Requires-Dist: redis
Requires-Dist: requests
